django_mail_model_template/__init__.py
django_mail_model_template/admin.py
django_mail_model_template/apps.py
django_mail_model_template/factory.py
django_mail_model_template/models.py
django_mail_model_template/utils.py
django_mail_model_template/migrations/0001_initial.py
django_mail_model_template/migrations/0002_mailtemplate_language_alter_mailtemplate_name_and_more.py
django_mail_model_template/migrations/0003_alter_mailtemplate_language_default_to_ja.py
django_mail_model_template/migrations/__init__.py
django_mail_model_template-0.1.2.dist-info/licenses/LICENSE
django_mail_model_template-0.1.2.dist-info/METADATA
django_mail_model_template-0.1.2.dist-info/WHEEL
django_mail_model_template-0.1.2.dist-info/top_level.txt
django_mail_model_template-0.1.2.dist-info/RECORD
